[
{"english": "Country", "vietnamese": "Quốc gia"},
{"english": "Nation", "vietnamese": "Quốc gia, dân tộc"},
{"english": "Continent", "vietnamese": "Châu lục"},
{"english": "Asia", "vietnamese": "Châu Á"},
{"english": "Europe", "vietnamese": "Châu Âu"},
{"english": "Africa", "vietnamese": "Châu Phi"},
{"english": "America", "vietnamese": "Châu Mỹ"},
{"english": "Australia", "vietnamese": "Châu Úc"},
{"english": "Vietnam", "vietnamese": "Việt Nam"},
{"english": "China", "vietnamese": "Trung Quốc"},
{"english": "Japan", "vietnamese": "Nhật Bản"},
{"english": "South Korea", "vietnamese": "Hàn Quốc"},
{"english": "Thailand", "vietnamese": "Thái Lan"},
{"english": "India", "vietnamese": "Ấn Độ"},
{"english": "USA", "vietnamese": "Mỹ"},
{"english": "UK", "vietnamese": "Anh"},
{"english": "France", "vietnamese": "Pháp"},
{"english": "Germany", "vietnamese": "Đức"},
{"english": "Italy", "vietnamese": "Ý"},
{"english": "Spain", "vietnamese": "Tây Ban Nha"},
{"english": "Canada", "vietnamese": "Canada"},
{"english": "Brazil", "vietnamese": "Brazil"},
{"english": "Russia", "vietnamese": "Nga"},
{"english": "Egypt", "vietnamese": "Ai Cập"},
{"english": "Mexico", "vietnamese": "Mexico"},
{"english": "Argentina", "vietnamese": "Argentina"},
{"english": "Indonesia", "vietnamese": "Indonesia"},
{"english": "Philippines", "vietnamese": "Philippines"}
]