[
{"english": "Appearance", "vietnamese": "Ngoại hình"},
{"english": "Height", "vietnamese": "Chiều cao"},
{"english": "Weight", "vietnamese": "Cân nặng"},
{"english": "Figure", "vietnamese": "Dáng người"},
{"english": "Slim", "vietnamese": "Mảnh mai"},
{"english": "Fit", "vietnamese": "Cân đối, khỏe mạnh"},
{"english": "Muscular", "vietnamese": "Cơ bắp, vạm vỡ"},
{"english": "Overweight", "vietnamese": "Thừa cân"},
{"english": "Tall", "vietnamese": "Cao"},
{"english": "Short", "vietnamese": "Thấp, lùn"},
{"english": "Skin tone", "vietnamese": "Màu da"},
{"english": "Pale", "vietnamese": "Da nhợt nhạt"},
{"english": "Tan", "vietnamese": "Da rám nắng"},
{"english": "Dark-skinned", "vietnamese": "Da ngăm"},
{"english": "Face shape", "vietnamese": "Hình dáng khuôn mặt"},
{"english": "Round face", "vietnamese": "Khuôn mặt tròn"},
{"english": "Oval face", "vietnamese": "Khuôn mặt trái xoan"},
{"english": "Square face", "vietnamese": "Khuôn mặt vuông"},
{"english": "Hair", "vietnamese": "Tóc"},
{"english": "Curly hair", "vietnamese": "Tóc xoăn"},
{"english": "Straight hair", "vietnamese": "Tóc thẳng"},
{"english": "Wavy hair", "vietnamese": "Tóc gợn sóng"},
{"english": "Bald", "vietnamese": "Hói đầu"},
{"english": "Eye color", "vietnamese": "Màu mắt"},
{"english": "Blue eyes", "vietnamese": "Mắt xanh"},
{"english": "Brown eyes", "vietnamese": "Mắt nâu"},
{"english": "Hazel eyes", "vietnamese": "Mắt nâu lục nhạt"},
{"english": "Attractive", "vietnamese": "Thu hút, ưa nhìn"},
{"english": "Handsome", "vietnamese": "Đẹp trai"},
{"english": "Beautiful", "vietnamese": "Xinh đẹp"}
]